pyup/__init__.py
pyup/__main__.py
pyup/atm.py
pyup/general.py
pyup/pomodoro.py
pyup/pyup.py
pyup/shop.py
pyup/task.py
PyUp_LifeUp_API-0.1.1.dist-info/LICENSE
PyUp_LifeUp_API-0.1.1.dist-info/METADATA
PyUp_LifeUp_API-0.1.1.dist-info/WHEEL
PyUp_LifeUp_API-0.1.1.dist-info/top_level.txt
PyUp_LifeUp_API-0.1.1.dist-info/RECORD
